drug2ways/__init__.py
drug2ways/__main__.py
drug2ways/alternative_graph_traversal.py
drug2ways/bel_helper.py
drug2ways/cli.py
drug2ways/cli_helper.py
drug2ways/constants.py
drug2ways/graph_processing.py
drug2ways/graph_reader.py
drug2ways/graph_traversal.py
drug2ways/pathway.py
drug2ways/permute.py
drug2ways/wrapper.py
drug2ways-0.0.2.dist-info/LICENSE
drug2ways-0.0.2.dist-info/METADATA
drug2ways-0.0.2.dist-info/WHEEL
drug2ways-0.0.2.dist-info/entry_points.txt
drug2ways-0.0.2.dist-info/top_level.txt
drug2ways-0.0.2.dist-info/RECORD
