Metadata-Version: 2.1
Name: drug2ways
Version: 0.0.2
Summary: Reasoning over polar paths in biological networks for drug discovery applications
Home-page: https://github.com/drug2ways/drug2ways
Author: Daniel Rivas Barragan and Daniel Domingo-Fernández
Author-email: daniel.rivas@bsc.es
Maintainer: Daniel Rivas Barragan and Daniel Domingo-Fernández
Maintainer-email: danieldomingofernandez@hotmail.com
License: Apache 2.0 License
Download-URL: https://github.com/drug2ways/drug2ways
Project-URL: Bug Tracker, https://github.com/drug2ways/drug2ways/issues
Project-URL: Source Code, https://github.com/drug2ways/drug2ways
Project-URL: Documentation, https://drug2ways.readthedocs.io
Keywords: Systems Biology,Networks Biology,Bioinformatics,Network Algorithms,Drug Discovery
Platform: UNKNOWN
Classifier: Development Status :: 4 - Beta
Classifier: Environment :: Console
Classifier: Intended Audience :: Developers
Classifier: Intended Audience :: Science/Research
Classifier: License :: OSI Approved :: Apache Software License
Classifier: Operating System :: OS Independent
Classifier: Programming Language :: Python
Classifier: Programming Language :: Python :: 3.7
Classifier: Programming Language :: Python :: 3.6
Classifier: Programming Language :: Python :: 3 :: Only
Classifier: Topic :: Scientific/Engineering :: Bio-Informatics
Classifier: Topic :: Scientific/Engineering :: Mathematics
Requires-Python: >=3.5
Requires-Dist: click (==7.1.1)
Requires-Dist: tqdm
Requires-Dist: networkx (>=2.1)
Requires-Dist: pandas (==1.0.3)
Requires-Dist: numpy
Requires-Dist: scipy
Requires-Dist: statsmodels
Requires-Dist: pybel
Provides-Extra: docs
Requires-Dist: sphinx ; extra == 'docs'
Requires-Dist: sphinx-rtd-theme ; extra == 'docs'
Requires-Dist: sphinx-click ; extra == 'docs'
Requires-Dist: sphinx-autodoc-typehints ; extra == 'docs'
Provides-Extra: speed
Requires-Dist: mpi4py ; extra == 'speed'
